[
  {
    "id": "meinp30mfc4228rxwg",
    "nomeCompleto": "Andre Violaro",
    "dataAniversario": "23/09",
    "empresa": "Velotax",
    "dataContratado": "",
    "status": "Ativo",
    "cargo": "Analista",
    "email": "andre@velotax.com",
    "telefone": "(11) 99999-9999",
    "endereco": "Rua Teste, 123",
    "acessos": [],
    "desligado": false,
    "dataDesligamento": "",
    "afastado": false,
    "dataAfastamento": "",
    "createdAt": "2025-08-19T14:45:55.463Z",
    "updatedAt": "2025-08-19T14:45:55.463Z"
  },
  {
    "id": "teste123",
    "nomeCompleto": "João Silva",
    "dataAniversario": "15/03",
    "empresa": "Velotax",
    "dataContratado": "01/01/2025",
    "status": "Ativo",
    "cargo": "Desenvolvedor",
    "email": "joao@velotax.com",
    "telefone": "(11) 88888-8888",
    "endereco": "Av. Principal, 456",
    "acessos": [],
    "desligado": false,
    "dataDesligamento": "",
    "afastado": false,
    "dataAfastamento": "",
    "createdAt": "2025-08-19T14:45:55.463Z",
    "updatedAt": "2025-08-19T14:45:55.463Z"
  }
]
